<?xml version="1.0" encoding="UTF-8"?>
<loginTicketRequest version="1.0">
  <header>
    <source>serialNumber=CUIT 30708808489,emailAddress=madedu@mfdsolutions.com.ar,CN=MADEDU,OU=MADEDU,O=MADEDU,ST=Buenos Aires,C=AR</source>
    <destination>serialNumber=CUIT 33693450239, CN=wsaahomo, O=afip, C=ar</destination>
    <uniqueId>4325399</uniqueId>
    <generationTime>2008-02-25T12:00:00-03:00</generationTime>
    <expirationTime>2008-02-25T12:10:00-03:00</expirationTime>
  </header>
  <service>wsfe</service>
</loginTicketRequest>